pytadolog/__init__.py
pytadolog/__main__.py
pytadolog/datalogger.py
pytadolog/datastores.py
pytadolog/extended_interface.py
pytadolog/utils.py
pytadolog-1.0.0.data/scripts/csv2excel.py
pytadolog-1.0.0.dist-info/LICENSE
pytadolog-1.0.0.dist-info/METADATA
pytadolog-1.0.0.dist-info/WHEEL
pytadolog-1.0.0.dist-info/entry_points.txt
pytadolog-1.0.0.dist-info/top_level.txt
pytadolog-1.0.0.dist-info/RECORD
