Metadata-Version: 2.1
Name: pytadolog
Version: 1.0.0
Summary: CSV logger for PyTado
Home-page: https://github.com/jjgibson/PyTadoLog
Author: Josh Gibson
Author-email: josh-gibson@outlook.com
License: MIT
Keywords: tado,python,logging
Platform: any
Classifier: Development Status :: 3 - Alpha
Classifier: Topic :: Home Automation
Classifier: Intended Audience :: Developers
Classifier: License :: OSI Approved :: MIT License
Classifier: Natural Language :: English
Classifier: Programming Language :: Python :: 3
Classifier: Programming Language :: Python :: 3.6
Requires-Python: >=3.6
Requires-Dist: keyring
Requires-Dist: numpy
Requires-Dist: openpyxl
Requires-Dist: pandas
